atikin_env/__init__.py
atikin_env/core.py
atikin_env/exceptions.py
atikin_env/parser.py
atikin_env-1.0.0.dist-info/licenses/LICENSE
tests/test_basic.py
tests/test_type_cast.py
atikin_env-1.0.0.dist-info/METADATA
atikin_env-1.0.0.dist-info/WHEEL
atikin_env-1.0.0.dist-info/top_level.txt
atikin_env-1.0.0.dist-info/RECORD
