Metadata-Version: 2.4
Name: atikin-env
Version: 1.0.0
Summary: Ultra-fast, zero-dependency dotenv alternative with type casting
Author-email: Atikin Verse <contact@atikinverse.com>
License: MIT License
Classifier: Programming Language :: Python :: 3
Classifier: License :: OSI Approved :: MIT License
Classifier: Operating System :: OS Independent
Requires-Python: >=3.7
License-File: LICENSE
Dynamic: license-file
